Workbook
Name aporte: Controle!$D$13
Name patrimonio: Controle!$D$16
Name qtd_anos: Controle!$D$14
Name Rendimento_Carteira: Controle!$D$9
Name salario: Controle!$D$8
Name sugestao_investimento: Controle!$D$10
Name taxa_mensal: Controle!$D$15

Sheet Controle
B7: Configurações | H7: PERFIL | I7: Conservador
B8: Salário | D8: 2000 | H8: VALOR A SER INVESTIDO POR MÊS | I8: =aporte -> 150
B9: Rendimento da Carteira | D9: 0.007
B10: Sugestão de Investimento (30%) | D10: =D8*30% -> 600 | H10: Tipo de FII | I10: Percentual Sugerido | J10: Valores
H11: PAPEL | I11: =VLOOKUP($I$7&"-"&H11,Planilha2!$A:$D,4,FALSE) -> 0.35 | J11: =I11*$I$8 -> 52.5
B12: Investimento Mensal | H12: TIJOLO | I12: =VLOOKUP($I$7&"-"&H12,Planilha2!$A:$D,4,FALSE) -> 0.55 | J12: =I12*$I$8 -> 82.5
B13: Quanto investir por mês ? | D13: 150 | H13: HÍBRIDOS | I13: =VLOOKUP($I$7&"-"&H13,Planilha2!$A:$D,4,FALSE) -> 0.05 | J13: =I13*$I$8 -> 7.5
B14: Por quantos anos ? | D14: 4 | H14: FOFs | I14: =VLOOKUP($I$7&"-"&H14,Planilha2!$A:$D,4,FALSE) -> 0.05 | J14: =I14*$I$8 -> 7.5
B15: Taxa de rendimento mensal ? | D15: 0.01079 | H15: DESENVOLVIMENTO | I15: =VLOOKUP($I$7&"-"&H15,Planilha2!$A:$D,4,FALSE) -> 0 | J15: =I15*$I$8 -> 0
B16: Patrimônio acumulado ? | D16: =FV(taxa_mensal,qtd_anos*12,aporte*-1) -> 9368.1529 | H16: HOTELARIAS | I16: =VLOOKUP($I$7&"-"&H16,Planilha2!$A:$D,4,FALSE) -> 0 | J16: =I16*$I$8 -> 0
B17: Dividendos mensais ? | D17: =patrimonio*Rendimento_Carteira -> 65.577071 | J17: =SUM(J11:J16) -> 150
A20: 2 | B20: Cenários e Previsões | C20: Patrimônio | D20: Dividendos
A21: 5 | B21: Quanto em 2 anos ? | C21: =FV($D$15,$A20*12,$D$13*-1) -> 4084.1441 | D21: =C21*Rendimento_Carteira -> 28.589009
A22: 10 | B22: Quanto em 5 anos ? | C22: =FV($D$15,$A21*12,$D$13*-1) -> 12566.537 | D22: =C22*Rendimento_Carteira -> 87.96576
A23: 20 | B23: Quanto em 10 anos ? | C23: =FV($D$15,$A22*12,$D$13*-1) -> 36492.632 | D23: =C23*Rendimento_Carteira -> 255.44842
A24: 30 | B24: Quanto em 20 anos ? | C24: =FV($D$15,$A23*12,$D$13*-1) -> 168779.76 | D24: =C24*Rendimento_Carteira -> 1181.4583
B25: Quanto em 30 anos ? | C25: =FV($D$15,$A24*12,$D$13*-1) -> 648325.45 | D25: =C25*Rendimento_Carteira -> 4538.2781

Sheet Planilha2
A2: CHAVE | B2: PERFIL | C2: TIPO DE FII | D2: %
A3: =B3&"-"&C3 -> Conservador-PAPEL | B3: Conservador | C3: PAPEL | D3: 0.35 | H3: %
A4: =B4&"-"&C4 -> Conservador-TIJOLO | B4: Conservador | C4: TIJOLO | D4: 0.55 | G4: Moderado-TIJOLO | H4: =VLOOKUP(G4,$A:$D,4,FALSE) -> 0.37
A5: =B5&"-"&C5 -> Conservador-HÍBRIDOS | B5: Conservador | C5: HÍBRIDOS | D5: 0.05
A6: =B6&"-"&C6 -> Conservador-FOFs | B6: Conservador | C6: FOFs | D6: 0.05
A7: =B7&"-"&C7 -> Conservador-DESENVOLVIMENTO | B7: Conservador | C7: DESENVOLVIMENTO | D7: 0
A8: =B8&"-"&C8 -> Conservador-HOTELARIAS | B8: Conservador | C8: HOTELARIAS | D8: 0
A9: =B9&"-"&C9 -> Moderado-PAPEL | B9: Moderado | C9: PAPEL | D9: 0.3
A10: =B10&"-"&C10 -> Moderado-TIJOLO | B10: Moderado | C10: TIJOLO | D10: 0.37
A11: =B11&"-"&C11 -> Moderado-HÍBRIDOS | B11: Moderado | C11: HÍBRIDOS | D11: 0.1
A12: =B12&"-"&C12 -> Moderado-FOFs | B12: Moderado | C12: FOFs | D12: 0.07
A13: =B13&"-"&C13 -> Moderado-DESENVOLVIMENTO | B13: Moderado | C13: DESENVOLVIMENTO | D13: 0.08
A14: =B14&"-"&C14 -> Moderado-HOTELARIAS | B14: Moderado | C14: HOTELARIAS | D14: 0.08
A15: =B15&"-"&C15 -> Agressivo-PAPEL | B15: Agressivo | C15: PAPEL | D15: 0.25
A16: =B16&"-"&C16 -> Agressivo-TIJOLO | B16: Agressivo | C16: TIJOLO | D16: 0.3
... A20: =B20&"-"&C20 -> Agressivo-HOTELARIAS | B20: Agressivo | C20: HOTELARIAS | D20: 0.1
